Lab93_Finance/__init__.py
Lab93_Finance/__main__.py
Lab93_Finance/account/__init__.py
Lab93_Finance/account/__main__.py
Lab93_Finance/account/assets/__init__.py
Lab93_Finance/account/assets/__main__.py
Lab93_Finance/account/positions/__init__.py
Lab93_Finance/account/positions/__main__.py
Lab93_Finance/data/__init__.py
Lab93_Finance/data/__main__.py
Lab93_Finance/data/historic/__init__.py
Lab93_Finance/data/historic/__main__.py
Lab93_Finance/data/live/__init__.py
Lab93_Finance/data/live/__main__.py
Lab93_Finance/data/live/stream/__init__.py
Lab93_Finance/graphing/__init__.py
Lab93_Finance/graphing/__main__.py
Lab93_Finance/graphing/old.__init__.py
Lab93_Finance/graphing/CandlestickGraphs/__init__.py
Lab93_Finance/graphing/CandlestickGraphs/__main__.py
Lab93_Finance/graphing/LinearRegression/__init__.py
Lab93_Finance/graphing/LinearRegression/__main__.py
Lab93_Finance/graphing/MovingCrossAverage/__init__.py
Lab93_Finance/graphing/MovingCrossAverage/__main__.py
Lab93_Finance/reporting/__init__.py
Lab93_Finance/trading/__init__.py
Lab93_Finance-0.0.1.4.dist-info/METADATA
Lab93_Finance-0.0.1.4.dist-info/WHEEL
Lab93_Finance-0.0.1.4.dist-info/top_level.txt
Lab93_Finance-0.0.1.4.dist-info/RECORD
