Metadata-Version: 2.1
Name: Lab93-Finance
Version: 0.0.1.4
Summary: A library for handling and managing finance accounts algorithmically.
Author-email: Hunter Dale <hunter@guyyatsu.me>
Project-URL: Homepage, https://github.com/Lab-93/Finance
Project-URL: Bug Tracker, https://github.com/Lab-93/Finance/issues
Classifier: Programming Language :: Python :: 3
Classifier: License :: OSI Approved :: MIT License
Classifier: Operating System :: OS Independent
Requires-Python: >=3.7
Requires-Dist: Lab93Cryptogram
Requires-Dist: Lab93-DatabaseSystem
Requires-Dist: plotly
Requires-Dist: kaleido
Requires-Dist: alpaca-py
